di/__init__.py
di/bean.py
di/ctx.py
di/decorator.py
di/ref.py
di/utils.py
Simple_PyDI-0.9.0.dist-info/METADATA
Simple_PyDI-0.9.0.dist-info/WHEEL
Simple_PyDI-0.9.0.dist-info/top_level.txt
Simple_PyDI-0.9.0.dist-info/RECORD
