Metadata-Version: 2.1
Name: Simple-PyDI
Version: 0.9.0
Summary: simple di framework like java spring-framework
Home-page: https://github.com/Tasse00/pydi
Author: Carl.Zhang
Author-email: tasse_00@163.com
Maintainer: Carl.Zhang
Maintainer-email: tasse_00@163.com
License: BSD License
Platform: all
Classifier: Programming Language :: Python :: 3
Classifier: License :: OSI Approved :: BSD License
Classifier: Operating System :: OS Independent
